{
  "project_info": {
    "project_number": "295913213710",
    "project_id": "tu-parque-bo",
    "storage_bucket": "tu-parque-bo.firebasestorage.app"
  },
  "client": [
    {
      "client_info": {
        "mobilesdk_app_id": "1:295913213710:android:5b387e3211728b1b64d15f",
        "android_client_info": {
          "package_name": "com.techsolutionsstudio.tu_parqueo"
        }
      },
      "oauth_client": [],
      "api_key": [
        {
          "current_key": "AIzaSyBjjEEDzJywIL4888YOOVkJlw2b8FOSIo8"
        }
      ],
      "services": {
        "appinvite_service": {
          "other_platform_oauth_client": []
        }
      }
    }
  ],
  "configuration_version": "1"
}